asdff-0.2.1.dist-info/METADATA
asdff-0.2.1.dist-info/WHEEL
asdff-0.2.1.dist-info/licenses/LICENSE
asdff/__init__.py
asdff/__version__.py
asdff/base.py
asdff/sd.py
asdff/utils.py
asdff/yolo.py
asdff-0.2.1.dist-info/RECORD
