Metadata-Version: 2.1
Name: asdff
Version: 0.2.1
Summary: custom pipeline for auto inpainting
Author-Email: Bingsu <ks2515@naver.com>
License: AGPL-3.0
Project-URL: Repository, https://github.com/Bing-su/asdff
Requires-Python: >=3.8
Requires-Dist: diffusers[torch]>=0.19.0
Requires-Dist: transformers>=4.25.1
Requires-Dist: ultralytics
